poloniex/__init__.py
poloniex/concurrency.py
poloniex/exceptions.py
poloniex/poloniex.py
poloniex/utils.py
poloniex-0.0.15.dist-info/DESCRIPTION.rst
poloniex-0.0.15.dist-info/METADATA
poloniex-0.0.15.dist-info/RECORD
poloniex-0.0.15.dist-info/WHEEL
poloniex-0.0.15.dist-info/metadata.json
poloniex-0.0.15.dist-info/top_level.txt
