Metadata-Version: 2.0
Name: poloniex
Version: 0.0.15
Summary: Poloniex API client for humans
Home-page: http://github.com/Aula13/poloniex
Author: Enrico Bacis, Daniele Ciriello
Author-email: enrico.bacis@gmail.com, ciriello.daniele@gmail.com
License: MIT
Keywords: poloniex cryptocurrency cryptocurrencies api client bitcoin
Platform: UNKNOWN
Requires-Dist: requests
Requires-Dist: six
